airthings/__init__.py
airthings_cloud-0.2.0.dist-info/LICENSE
airthings_cloud-0.2.0.dist-info/METADATA
airthings_cloud-0.2.0.dist-info/WHEEL
airthings_cloud-0.2.0.dist-info/top_level.txt
airthings_cloud-0.2.0.dist-info/RECORD
